setup.py
asyncytmusicapi/__init__.py
asyncytmusicapi/constants.py
asyncytmusicapi/continuations.py
asyncytmusicapi/helpers.py
asyncytmusicapi/navigation.py
asyncytmusicapi/setup.py
asyncytmusicapi/ytmusic.py
asyncytmusicapi.egg-info/PKG-INFO
asyncytmusicapi.egg-info/SOURCES.txt
asyncytmusicapi.egg-info/dependency_links.txt
asyncytmusicapi.egg-info/requires.txt
asyncytmusicapi.egg-info/top_level.txt